README.rst
setup.py
climata/__init__.py
climata/base.py
climata/parsers.py
climata/version.py
climata.egg-info/PKG-INFO
climata.egg-info/SOURCES.txt
climata.egg-info/dependency_links.txt
climata.egg-info/requires.txt
climata.egg-info/top_level.txt
climata/acis/__init__.py
climata/acis/constants.py
climata/bin/acis_data.py
climata/bin/acis_sites.py
climata/cocorahs/__init__.py
climata/epa/__init__.py
climata/epa/constants.py
climata/fips/__init__.py
climata/huc8/__init__.py
climata/hydromet/__init__.py
climata/nws/__init__.py
climata/nws/parsers.py
climata/snotel/__init__.py
climata/usgs/__init__.py
climata/usgs/constants.py