Metadata-Version: 1.1
Name: climata
Version: 0.5.0
Summary: Loads climate and hydrology data from ACIS (NOAA RCCs), CoCoRaHS, Hydromet (USBR), SNOTEL AWDB (NRCS) and NWIS (USGS).
Home-page: https://github.com/heigeo/climata
Author: HEI Geo
Author-email: gis@houstoneng.com
License: MIT
Platform: UNKNOWN
Classifier: Development Status :: 4 - Beta
Classifier: Environment :: Web Environment
Classifier: License :: OSI Approved :: MIT License
Classifier: Programming Language :: Python :: 2
Classifier: Programming Language :: Python :: 2.7
Classifier: Programming Language :: Python :: 3
Classifier: Programming Language :: Python :: 3.4
Classifier: Programming Language :: Python :: 3.5
Classifier: Programming Language :: Python :: 3.6
Classifier: Natural Language :: English
Classifier: Intended Audience :: Science/Research
Classifier: Topic :: Scientific/Engineering :: GIS
Classifier: Topic :: Scientific/Engineering :: Information Analysis
Classifier: Topic :: System :: Networking :: Monitoring
